lz4inv-0.2.0.dist-info/METADATA
lz4inv-0.2.0.dist-info/WHEEL
lz4inv-0.2.0.dist-info/licenses/LICENSE
lz4inv/py.typed
lz4inv/__init__.py
lz4inv/lz4inv.pyi
lz4inv/lz4inv.cpython-313-x86_64-linux-gnu.so
lz4inv-0.2.0.dist-info/RECORD
