Metadata-Version: 2.4
Name: lz4inv
Version: 0.2.0
Classifier: Programming Language :: Rust
Classifier: Programming Language :: Python :: Implementation :: CPython
Classifier: Programming Language :: Python :: Implementation :: PyPy
Requires-Dist: pytest ; extra == 'tests'
Provides-Extra: tests
License-File: LICENSE
Summary: A Rust-backed Python module for decompressing data compressed with the modified LZ4 algorithm for an anime game.
Keywords: lz4,lz4inv,compression,decompression
Author-email: daflyinbed <1677759063@qq.com>
Maintainer-email: StarHeartHunt <starheart233@gmail.com>
License: MIT
Requires-Python: >=3.9
Project-URL: Homepage, https://github.com/MooncellWiki/lz4inv
Project-URL: Repository, https://github.com/MooncellWiki/lz4inv
